foundation_model_pkg/__init__.py
foundation_model_pkg/foundation_model.py
foundation_model_pkg/tools/__init__.py
foundation_model_pkg/tools/foundation_model.py
foundation_model_pkg/tools/utils.py
foundation_model_pkg/yamls/foundation_model.yaml
open_source_llm/__init__.py
open_source_llm/tools/__init__.py
open_source_llm/tools/open_source_llm.py
open_source_llm/tools/utils.py
open_source_llm/yamls/foundation_model.yaml
tests/__init__.py
tests/test_my_tool_1.py
open_source_llm_tool-0.0.1.dist-info/METADATA
open_source_llm_tool-0.0.1.dist-info/WHEEL
open_source_llm_tool-0.0.1.dist-info/entry_points.txt
open_source_llm_tool-0.0.1.dist-info/top_level.txt
open_source_llm_tool-0.0.1.dist-info/RECORD
